odoo/addons/account_invoice_reimbursable/README.rst
odoo/addons/account_invoice_reimbursable/__init__.py
odoo/addons/account_invoice_reimbursable/__manifest__.py
odoo/addons/account_invoice_reimbursable/i18n/account_invoice_reimbursable.pot
odoo/addons/account_invoice_reimbursable/i18n/de.po
odoo/addons/account_invoice_reimbursable/i18n/es.po
odoo/addons/account_invoice_reimbursable/i18n/tr.po
odoo/addons/account_invoice_reimbursable/models/__init__.py
odoo/addons/account_invoice_reimbursable/models/account_invoice.py
odoo/addons/account_invoice_reimbursable/readme/CONTRIBUTORS.rst
odoo/addons/account_invoice_reimbursable/readme/DESCRIPTION.rst
odoo/addons/account_invoice_reimbursable/readme/USAGE.rst
odoo/addons/account_invoice_reimbursable/security/ir.model.access.csv
odoo/addons/account_invoice_reimbursable/static/description/icon.png
odoo/addons/account_invoice_reimbursable/static/description/index.html
odoo/addons/account_invoice_reimbursable/tests/__init__.py
odoo/addons/account_invoice_reimbursable/tests/test_reimbursable.py
odoo/addons/account_invoice_reimbursable/views/account_invoice_view.xml
odoo/addons/account_invoice_reimbursable/views/report_invoice.xml
odoo12_addon_account_invoice_reimbursable-12.0.1.0.0.99.dev10.dist-info/METADATA
odoo12_addon_account_invoice_reimbursable-12.0.1.0.0.99.dev10.dist-info/WHEEL
odoo12_addon_account_invoice_reimbursable-12.0.1.0.0.99.dev10.dist-info/top_level.txt
odoo12_addon_account_invoice_reimbursable-12.0.1.0.0.99.dev10.dist-info/RECORD
